its_system_alerts/__init__.py
its_system_alerts/system/__init__.py
its_system_alerts/system/alerts/__init__.py
its_system_alerts/system/alerts/alert_tracker.py
its_system_alerts/system/alerts/behavior.py
its_system_alerts/system/alerts/cdeg_sts_vod_analysis.py
its_system_alerts/system/alerts/path_router_alerts.py
its_system_alerts/system/alerts/speed_alerts.py
tako_alerts_system-0.2.7.dist-info/METADATA
tako_alerts_system-0.2.7.dist-info/WHEEL
tako_alerts_system-0.2.7.dist-info/top_level.txt
tako_alerts_system-0.2.7.dist-info/RECORD
