Metadata-Version: 2.1
Name: tako-alerts-system
Version: 0.2.7
Summary: Read PyPI package information
Home-page: https://github.com/melius/itsTako_alerts_library
Author: Gabriel González
Author-email: gabriel.gonzalez@meliusid.com
Classifier: Programming Language :: Python :: 3
Classifier: License :: OSI Approved :: MIT License
Classifier: Operating System :: OS Independent
Requires-Python: >=3.10
